{"trial_id": "12", "hyperparameters": {"space": [{"class_name": "Choice", "config": {"name": "wd", "default": 0.002, "conditions": [], "values": [0.002, 0.004, 0.006], "ordered": true}}, {"class_name": "Choice", "config": {"name": "b1", "default": 0.8, "conditions": [], "values": [0.8, 0.9], "ordered": true}}, {"class_name": "Choice", "config": {"name": "b2", "default": 0.95, "conditions": [], "values": [0.95, 0.999], "ordered": true}}, {"class_name": "Choice", "config": {"name": "eps", "default": 1e-07, "conditions": [], "values": [1e-07, 3e-07], "ordered": true}}], "values": {"wd": 0.002, "b1": 0.9, "b2": 0.999, "eps": 3e-07}}, "metrics": {"metrics": {"loss": {"direction": "min", "observations": [{"value": [4.089573860168457], "step": 58}]}, "val_loss": {"direction": "min", "observations": [{"value": [3.684880018234253], "step": 58}]}}}, "score": 3.684880018234253, "best_step": 58, "status": "COMPLETED", "message": null}